scimma_aws_utils/__init__.py
scimma_aws_utils/auth.py
scimma_aws_utils/awscreds.py
scimma_aws_utils/cmd_login.py
scimma_aws_utils/cmd_setup.py
scimma_aws_utils/configs.py
scimma_aws_utils/credentials.py
scimma_aws_utils/main.py
scimma_aws_utils-1.1.3.dist-info/LICENSE
scimma_aws_utils-1.1.3.dist-info/METADATA
scimma_aws_utils-1.1.3.dist-info/WHEEL
scimma_aws_utils-1.1.3.dist-info/entry_points.txt
scimma_aws_utils-1.1.3.dist-info/top_level.txt
scimma_aws_utils-1.1.3.dist-info/RECORD
